objective/__init__.py
objective/core.py
objective/exc.py
objective/fields.py
objective/validation.py
objective/values.py
objective-0.0.13.dist-info/METADATA
objective-0.0.13.dist-info/RECORD
objective-0.0.13.dist-info/WHEEL
objective-0.0.13.dist-info/pbr.json
objective-0.0.13.dist-info/top_level.txt
