Metadata-Version: 2.1
Name: objective
Version: 0.0.13
Summary: declarative de/serialization of python structures
Home-page: https://github.com/diefans/objective
Author: Oliver Berger
Author-email: diefans@gmail.com
License: UNKNOWN
Keywords: serialization deserialization serialize deserialize declarative object objective schema validation
Platform: UNKNOWN
Classifier: Development Status :: 4 - Beta
Classifier: Intended Audience :: Developers
Classifier: License :: OSI Approved :: Apache Software License
Classifier: Intended Audience :: Developers
Classifier: Programming Language :: Python
Classifier: Programming Language :: Python :: 3.5
Requires-Dist: python-dateutil
Requires-Dist: pytz
Requires-Dist: validate-email
